npyt/__init__.py
npyt/_version.py
npyt/core.py
npyt/endless.py
npyt/format.py
npyt-0.4.2.dist-info/METADATA
npyt-0.4.2.dist-info/WHEEL
npyt-0.4.2.dist-info/licenses/LICENSE
npyt-0.4.2.dist-info/RECORD
