Metadata-Version: 2.4
Name: npyt
Version: 0.4.2
Summary: NPY file format with Tail
License-File: LICENSE
Requires-Python: >=3.8
Requires-Dist: loguru
Requires-Dist: more-itertools
Requires-Dist: numpy
Requires-Dist: typing-extensions
